astami/__init__.py
astami/client.py
astami/py.typed
astami-1.0.2.dist-info/METADATA
astami-1.0.2.dist-info/WHEEL
astami-1.0.2.dist-info/licenses/LICENSE
astami-1.0.2.dist-info/RECORD
