Metadata-Version: 2.4
Name: astami
Version: 1.0.2
Summary: Modern async/sync Asterisk Manager Interface (AMI) client for Python 3.10+
Project-URL: Homepage, https://github.com/andrewyager/astami
Project-URL: Documentation, https://astami.readthedocs.io
Project-URL: Repository, https://github.com/andrewyager/astami.git
Project-URL: Issues, https://github.com/andrewyager/astami/issues
Author-email: Andrew Yager <andrew@rwts.com.au>
License-Expression: MIT
License-File: LICENSE
Keywords: ami,asterisk,asyncio,pbx,telephony,voip
Classifier: Development Status :: 5 - Production/Stable
Classifier: Framework :: AsyncIO
Classifier: Intended Audience :: Developers
Classifier: Intended Audience :: Telecommunications Industry
Classifier: License :: OSI Approved :: MIT License
Classifier: Operating System :: OS Independent
Classifier: Programming Language :: Python :: 3
Classifier: Programming Language :: Python :: 3.10
Classifier: Programming Language :: Python :: 3.11
Classifier: Programming Language :: Python :: 3.12
Classifier: Programming Language :: Python :: 3.13
Classifier: Topic :: Communications :: Telephony
Classifier: Topic :: Software Development :: Libraries :: Python Modules
Classifier: Typing :: Typed
Requires-Python: >=3.10
Provides-Extra: dev
Requires-Dist: black>=24.0; extra == 'dev'
Requires-Dist: mypy>=1.9; extra == 'dev'
Requires-Dist: pytest-asyncio>=0.23; extra == 'dev'
Requires-Dist: pytest-cov>=4.0; extra == 'dev'
Requires-Dist: pytest>=8.0; extra == 'dev'
Requires-Dist: ruff>=0.3; extra == 'dev'
Provides-Extra: docs
Requires-Dist: mkdocs-material>=9.5; extra == 'docs'
Requires-Dist: mkdocs>=1.6; extra == 'docs'
